csvspoon/__init__.py
csvspoon/_cli.py
csvspoon/_version.py
csvspoon/spoon.py
csvspoon-1.1.3.dist-info/LICENSE
csvspoon-1.1.3.dist-info/METADATA
csvspoon-1.1.3.dist-info/WHEEL
csvspoon-1.1.3.dist-info/entry_points.txt
csvspoon-1.1.3.dist-info/top_level.txt
csvspoon-1.1.3.dist-info/RECORD
