Metadata-Version: 2.2
Name: csvspoon
Version: 1.1.3
Summary: A tool to manipulate csv files with headers.
Author-email: Jean-Benoist Leger <jb@leger.tf>
License: MIT
Project-URL: Homepage, https://gitlab.com/jbleger/csvspoon
Keywords: csv
Classifier: Development Status :: 3 - Alpha
Classifier: License :: OSI Approved :: MIT License
Classifier: Programming Language :: Python :: 3 :: Only
Requires-Python: >=3.5
License-File: LICENSE
Requires-Dist: argparse
Requires-Dist: argcomplete
Provides-Extra: test
Requires-Dist: pytest; extra == "test"
Requires-Dist: numpy; extra == "test"
